dfalchemy/__init__.py
dfalchemy/converters.py
dfalchemy/generators.py
dfalchemy/utils.py
dfalchemy-1.0.dist-info/LICENSE.txt
dfalchemy-1.0.dist-info/METADATA
dfalchemy-1.0.dist-info/WHEEL
dfalchemy-1.0.dist-info/top_level.txt
dfalchemy-1.0.dist-info/RECORD
