Metadata-Version: 2.1
Name: dfalchemy
Version: 1.0
Summary: Generate, convert and manage DataFrames easily — perfect for devs and teachers.
Home-page: https://github.com/zGamingTechz/DFAlchemy
Author: Bhavya Soni
Classifier: Programming Language :: Python :: 3
Classifier: Operating System :: OS Independent
Requires-Python: >=3.8
License-File: LICENSE.txt
Requires-Dist: pandas
Requires-Dist: faker
